.bumpversion.cfg
.nojekyll
.readthedocs.yaml
CONTRIBUTING.md
LICENSE
MANIFEST.in
Makefile
README.md
pyproject.toml
requirements.txt
setup.py
test.txt
docs/Makefile
docs/api.rst
docs/conf.py
docs/index.rst
docs/make.bat
docs/requirements.txt
docs/images/mappic+180.jpg
docs/images/mappic+280.jpg
docs/images/mappic+80.jpg
epispread/__init__.py
epispread/__main__.py
epispread/_version.py
epispread/skeleton.py
epispread.egg-info/PKG-INFO
epispread.egg-info/SOURCES.txt
epispread.egg-info/dependency_links.txt
epispread.egg-info/requires.txt
epispread.egg-info/top_level.txt
epispread/graph_classes/__init__.py
epispread/graph_classes/heat_map.py
epispread/graph_classes/time_series.py
epispread/images/mappic+180.jpg
epispread/images/mappic+280.jpg
epispread/images/mappic+80.jpg
epispread/tests/test-db.csv
epispread/tests/test-world.csv
epispread/tests/test_all.py
epispread/tests/data_files/file.csv