Metadata-Version: 2.1
Name: epispread
Version: 1.0.0
Summary: Tool for visualizing disease spread
Author-email: Sienna <scb2197@columbia.edu>
License: MIT License
Project-URL: repository, https://github.com/scb-school/epi-spread-visualizer
Classifier: Development Status :: 2 - Pre-Alpha
Classifier: Programming Language :: Python :: Implementation :: CPython
Classifier: Programming Language :: Python :: Implementation :: PyPy
Classifier: Programming Language :: Python :: 3
Classifier: Programming Language :: Python :: 3.7
Classifier: Programming Language :: Python :: 3.8
Classifier: Programming Language :: Python :: 3.9
Classifier: Programming Language :: Python :: 3.10
Classifier: Programming Language :: Python :: 3.11
Requires-Python: >=3.7
Provides-Extra: develop
License-File: LICENSE
